{
    "@context": "https://schema.org",
    "@type": "Article",
    "headline": "{{headline}}",
    "description": "{{description}}",
    "image": "{{image}}",
    "author": {
        "@type": "Person",
        "name": "Gusti Devitto",
        "url": "https://gustidevitto.com"
    },
    "publisher": {
        "@type": "Organization",
        "name": "gustidevitto.com",
        "logo": {
            "@type": "ImageObject",
            "url": "https://gustidevitto.com/favicon.ico"
        }
    },
    "datePublished": "{{last_updated}}",
    "dateModified": "{{last_updated}}",
    "mainEntityOfPage": {
        "@type": "WebPage",
        "@id": "{{canonical_url}}"
    }
}